nnvisualizertf.py
nnvisualizertf-0.7.dist-info/LICENSE.txt
nnvisualizertf-0.7.dist-info/WHEEL
nnvisualizertf-0.7.dist-info/METADATA
nnvisualizertf-0.7.dist-info/RECORD
