Metadata-Version: 2.1
Name: nnvisualizertf
Version: 0.7
Summary: Visualizing Tensorflow networks.
Author: Anton Krause
Classifier: Programming Language :: Python :: 3
Classifier: Operating System :: OS Independent
Classifier: License :: OSI Approved :: GNU General Public License v3 (GPLv3)
Classifier: Development Status :: 3 - Alpha
Classifier: Topic :: Documentation
Requires-Dist: matplotlib
Requires-Dist: numpy
Requires-Dist: tensorflow
Project-URL: changelog, https://github.com/akdd11/nn_visualizer/blob/main/README.md
Project-URL: homepage, https://github.com/akdd11/nn_visualizer
